pocket_mongo/__init__.py
pocket_mongo/base_collection.py
pocket_mongo/exceptions.py
pocket_mongo/settings.py
tests/__init__.py
tests/test_connection.py
pocket_mongo-0.0.2.dist-info/LICENSE
pocket_mongo-0.0.2.dist-info/METADATA
pocket_mongo-0.0.2.dist-info/WHEEL
pocket_mongo-0.0.2.dist-info/top_level.txt
pocket_mongo-0.0.2.dist-info/RECORD
