Metadata-Version: 2.1
Name: pocket-mongo
Version: 0.0.2
Summary: An easy-to-use and quick setup interface for MongoDB.
Home-page: https://github.com/gssbruno/pocket-mongo
Author: Bruno Gonçalves dos Santos
Author-email: brunogoncalves.santos@gmail.com
License: UNKNOWN
Platform: UNKNOWN
Classifier: Programming Language :: Python :: 3
Classifier: License :: OSI Approved :: MIT License
Classifier: Operating System :: OS Independent
Requires-Python: >=3.6
